README
setup.py
bootlegger/__init__.py
bootlegger/api.py
bootlegger/cli.py
bootlegger/cryptfile.py
bootlegger.egg-info/PKG-INFO
bootlegger.egg-info/SOURCES.txt
bootlegger.egg-info/dependency_links.txt
bootlegger.egg-info/entry_points.txt
bootlegger.egg-info/requires.txt
bootlegger.egg-info/top_level.txt