Metadata-Version: 1.0
Name: bootlegger
Version: 1.1.1
Summary: Command Line Interface to Speakeasy
Home-page: UNKNOWN
Author: Zhehao Mao
Author-email: zhehao.mao@gmail.com
License: UNKNOWN
Platform: UNKNOWN
